app/logger.py
loggerInfo-0.0.1.dist-info/METADATA
loggerInfo-0.0.1.dist-info/WHEEL
loggerInfo-0.0.1.dist-info/dependency_links.txt
loggerInfo-0.0.1.dist-info/top_level.txt
loggerInfo-0.0.1.dist-info/RECORD
