Metadata-Version: 2.1
Name: loggerInfo
Version: 0.0.1
Summary: display of logs in project development
Home-page: UNKNOWN
Author: Wesley Marques
License: UNKNOWN
Platform: UNKNOWN
Classifier: Programming Language :: Python :: 3
Classifier: License :: OSI Approved :: MIT License
Classifier: Operating System :: OS Independent
Requires-Python: >=3.8
